elementum/__init__.py
elementum-0.0.8.dist-info/METADATA
elementum-0.0.8.dist-info/WHEEL
elementum-0.0.8.dist-info/licenses/LICENSE.txt
elementum-0.0.8.dist-info/RECORD
