Metadata-Version: 2.4
Name: elementum
Version: 0.0.8
Summary: A python module for getting information on the elements.
Project-URL: Homepage, https://github.com/Person12345678910111213141516/element
Project-URL: Issues, https://github.com/Person12345678910111213141516/element
Author: Person1234
License-File: LICENSE.txt
Classifier: License :: OSI Approved :: GNU General Public License v3 (GPLv3)
Classifier: Programming Language :: Python :: 3
Classifier: Topic :: Scientific/Engineering :: Chemistry
Requires-Python: >=3.0
